LICENSE
MANIFEST.in
NOTICE
README.rst
setup.py
./FlashXTest/__init__.py
./FlashXTest/__meta__.py
./FlashXTest.egg-info/PKG-INFO
./FlashXTest.egg-info/SOURCES.txt
./FlashXTest.egg-info/dependency_links.txt
./FlashXTest.egg-info/requires.txt
./FlashXTest.egg-info/top_level.txt
./FlashXTest/api/__init__.py
./FlashXTest/api/_checkSuite.py
./FlashXTest/api/_dryRun.py
./FlashXTest/api/_init.py
./FlashXTest/api/_manageSuite.py
./FlashXTest/api/_runSuite.py
./FlashXTest/api/_setupSuite.py
./FlashXTest/api/_webview.py
./FlashXTest/backend/__init__.py
./FlashXTest/backend/FlashTest/ERROR
./FlashXTest/backend/FlashTest/__init__.py
./FlashXTest/backend/FlashTest/configBase
./FlashXTest/backend/FlashTest/configTemplate
./FlashXTest/backend/FlashTest/createInfoFile.py
./FlashXTest/backend/FlashTest/error.sh
./FlashXTest/backend/FlashTest/exeScript
./FlashXTest/backend/FlashTest/flashTest.py
./FlashXTest/backend/FlashTest/temp_pidFile.py
./FlashXTest/backend/FlashTest/test.py
./FlashXTest/backend/FlashTest/lib/__init__.py
./FlashXTest/backend/FlashTest/lib/archive.py
./FlashXTest/backend/FlashTest/lib/createDotUploadFiles.py
./FlashXTest/backend/FlashTest/lib/extractUniqueBenchmarks.py
./FlashXTest/backend/FlashTest/lib/flashModule.py
./FlashXTest/backend/FlashTest/lib/flashTestParser.py
./FlashXTest/backend/FlashTest/lib/getProcessResults.py
./FlashXTest/backend/FlashTest/lib/layeredDict.py
./FlashXTest/backend/FlashTest/lib/logfile.py
./FlashXTest/backend/FlashTest/lib/makeSlimCopy.py
./FlashXTest/backend/FlashTest/lib/pidFile.py
./FlashXTest/backend/FlashTest/lib/py3_layeredDict.py
./FlashXTest/backend/FlashTest/lib/remoteFile.py
./FlashXTest/backend/FlashTest/lib/secondsToHuman.py
./FlashXTest/backend/FlashTest/lib/strategyTemplates.py
./FlashXTest/backend/FlashTest/lib/testObject.py
./FlashXTest/backend/FlashTest/lib/xmlNode.py
./FlashXTest/backend/FlashTest/scripts/TestInfo_changeNode.py
./FlashXTest/backend/FlashTest/scripts/__init__.py
./FlashXTest/backend/FlashTest/scripts/changeInfoFiles
./FlashXTest/backend/FlashTest/scripts/restarttest/__init__.py
./FlashXTest/backend/FlashTest/scripts/restarttest/restarttest.sh
./FlashXTest/cli/__init__.py
FlashXTest/backend/FlashTest/FlashXTest.egg-info/PKG-INFO
FlashXTest/backend/FlashTest/FlashXTest.egg-info/SOURCES.txt
FlashXTest/backend/FlashTest/FlashXTest.egg-info/dependency_links.txt
FlashXTest/backend/FlashTest/FlashXTest.egg-info/requires.txt
FlashXTest/backend/FlashTest/FlashXTest.egg-info/top_level.txt
