Metadata-Version: 2.1
Name: FlashXTest
Version: 2023.11
Author: The Flash-X Team
License: MIT License
Classifier: Programming Language :: Python :: 3.8
License-File: LICENSE
License-File: NOTICE
Requires-Dist: click
Requires-Dist: six
Requires-Dist: argparse
Requires-Dist: pyyaml
Requires-Dist: toml
